{
  "schemaVersion": 1,
  "id": "justhammers",
  "version": "${version}",
  "name": "Just Hammers",
  "description": "Just Hammers!",
  "authors": [
    "ErrorMikey"
  ],
  "contact": {
    "homepage": "https://fabricmc.net/",
    "sources": "https://github.com/FabricMC/fabric-example-mod"
  },
  "license": "GPL3",
  "icon": "assets/justhammers/icon.png",
  "environment": "*",
  "entrypoints": {
    "main": [
      "pro.mikey.justhammers.fabric.HammersFabric"
    ]
  },
  "mixins": [
    "justhammers-common.mixins.json",
    "justhammers.mixins.json"
  ],
  "depends": {
    "fabric": "*",
    "minecraft": ">=1.18.2",
    "architectury": ">=4.9.83"
  }
}
